__init__.py
anonymizer.py
setup.py
tests.py
requests_anonymizer.egg-info/PKG-INFO
requests_anonymizer.egg-info/SOURCES.txt
requests_anonymizer.egg-info/dependency_links.txt
requests_anonymizer.egg-info/requires.txt
requests_anonymizer.egg-info/top_level.txt